{
  "calc": {
    "A_cover_mu": 159.99992000004,
    "q_avail_m3ph": 480.0,
    "t_win_h": 20.0,
    "d_target_mm": 90.0,
    "active_pumps": [
      "P1",
      "P2"
    ],
    "filtered_by_feed_by": 0,
    "allowed_zones": null,
    "skipped_null_wl_count": 42,
    "skipped_null_wl_fields": [
      "S3-G2-F1",
      "S3-G5-F3",
      "S3-G7-F5",
      "S3-G10-F7",
      "5",
      "S3-G3-F2",
      "16",
      "S3-G8-F6",
      "S3-G11-F8",
      "S4-G20-F14",
      "S4-G22-F16",
      "S8-G53-F36",
      "42",
      "43",
      "S6-G37-F25",
      "S6-G39-F26",
      "S6-G42-F28",
      "S7-G49-F32",
      "S7-G50-F33",
      "S7-G51-F34",
      "S8-G52-F35",
      "S6-G40-F27",
      "S7-G47-F31",
      "S4-G24-F18",
      "23",
      "S5-G27-F19",
      "S5-G29-F20",
      "S5-G30-F21",
      "S5-G32-F22",
      "S5-G33-F23",
      "S5-G35-F24",
      "S6-G45-F30",
      "S3-G6-F4",
      "10",
      "S4-G14-F9",
      "S4-G17-F11",
      "S4-G19-F13",
      "S4-G21-F15",
      "S4-G23-F17",
      "S4-G15-F10",
      "S4-G18-F12",
      "S6-G43-F29"
    ]
  },
  "drainage_targets": [],
  "batches": [],
  "steps": [],
  "total_eta_h": 0.0,
  "total_deficit_m3": 0.0
}